async_sqlalchemy_bridge/__init__.py
async_sqlalchemy_bridge/async_database.py
async_sqlalchemy_bridge/connector.py
async_sqlalchemy_bridge/props.py
async_sqlalchemy_bridge/repository.py
async_sqlalchemy_bridge/types.py
async_sqlalchemy_bridge-1.0.0.dist-info/METADATA
async_sqlalchemy_bridge-1.0.0.dist-info/WHEEL
async_sqlalchemy_bridge-1.0.0.dist-info/top_level.txt
async_sqlalchemy_bridge-1.0.0.dist-info/RECORD
