Metadata-Version: 2.1
Name: async-sqlalchemy-bridge
Version: 1.0.0
Summary: The async library for easy connect to postgres database
Author: MSNLP
Requires-Python: >=3.8
Requires-Dist: asyncpg <=1.0.0,>=0.29.0
Requires-Dist: greenlet <=4.0.0,>=3.0.3
Requires-Dist: pydantic <=3.0.0,>=2.6.1
Requires-Dist: SQLAlchemy <=3.0.0,>=2.0.27
